nacos_ai/__init__.py
nacos_ai/nacos_ai_client.py
nacos_ai/common/__init__.py
nacos_ai/common/ai_client_config.py
nacos_ai/common/ai_client_config_builder.py
nacos_ai/common/auth.py
nacos_ai/common/constants.py
nacos_ai/common/nacos_exception.py
nacos_ai/common/utils.py
nacos_ai/mcp/__init__.py
nacos_ai/mcp/nacos_mcp_service.py
nacos_ai/mcp/model/__init__.py
nacos_ai/mcp/model/nacos_mcp_info.py
nacos_ai/mcp/model/registry_mcp_info.py
nacos_ai/transport/__init__.py
nacos_ai/transport/auth_client.py
nacos_ai/transport/client_http_proxy.py
nacos_ai/transport/http_agent.py
nacos_ai_sdk_python-0.1.0.dist-info/licenses/LICENSE
nacos_ai_sdk_python-0.1.0.dist-info/METADATA
nacos_ai_sdk_python-0.1.0.dist-info/WHEEL
nacos_ai_sdk_python-0.1.0.dist-info/top_level.txt
nacos_ai_sdk_python-0.1.0.dist-info/RECORD
