Metadata-Version: 2.4
Name: nacos-ai-sdk-python
Version: 0.1.0
Summary: Python sdk support mcp server auto register to nacos
Home-page: https://github.com/nacos-group/nacos-ai-sdk-python.git
Author: nacos
License: Apache License 2.0
Classifier: Topic :: Software Development :: Libraries :: Python Modules
Classifier: Operating System :: OS Independent
Classifier: Programming Language :: Python
Classifier: Programming Language :: Python :: 3.7
Requires-Python: >=3.7
License-File: LICENSE
Requires-Dist: aiohttp>=3.8.6
Requires-Dist: pydantic>=2.5.3
Dynamic: author
Dynamic: classifier
Dynamic: description
Dynamic: description-content-type
Dynamic: home-page
Dynamic: license
Dynamic: license-file
Dynamic: requires-dist
Dynamic: requires-python
Dynamic: summary
